Workbook
Name Slicer_month: #N/A
Name Slicer_Product_Name: #N/A
Name Slicer_Region: #N/A
Name Slicer_year: #N/A

Sheet Dashboard
S1: =GETPIVOTDATA("Total_Amount",'pivot and charts'!$A$2) -> 229192.47
S2: =GETPIVOTDATA("Total_Amount",'pivot and charts'!$A$8,"year",2024) -> 160444.73
S3: =GETPIVOTDATA("Total_Amount",'pivot and charts'!$A$8,"year",2025) -> 68747.74
S4: =GETPIVOTDATA("Sum of Total_Amount",'pivot and charts'!$A$12,"year",2025) -> -0.57151762
S5: =GETPIVOTDATA("Transaction_ID",'pivot and charts'!$A$4) -> 250
S6: =GETPIVOTDATA("Quantity",'pivot and charts'!$A$6) -> 753

Sheet top Customers
D1: Customer_Name | E1: Sum of Total_Amount
D2: Barbara Young | E2: 10649.8
D3: Daniel King | E3: 7309.8
D4: Dorothy Nelson | E4: 8269.79
D5: Edward Mitchell | E5: 11919.77
D6: Joseph Jackson | E6: 6949.84
D7: Karen Hill | E7: 8009.77
D8: Lawrence Reed | E8: 6989.77
D9: Mark Carter | E9: 15659.65
D10: Patricia Moore | E10: 9799.73
D11: Paul Baker | E11: 8309.74
D12: Grand Total | E12: 93867.66

Sheet Top Products
D1: Row Labels | E1: Sum of Quantity
D2: Blender | E2: 87
D3: Bookshelf | E3: 102
D4: Coffee Maker | E4: 39
D5: Desk | E5: 78
D6: Headphones | E6: 47
D7: Keyboard | E7: 89
D8: Laptop | E8: 75
D9: Monitor | E9: 88
D10: Office Chair | E10: 52
D11: Smartphone | E11: 96
D12: Grand Total | E12: 753

Sheet pivot and charts
A2: Sum of Total_Amount
A3: 229192.47
A4: Count of Transaction_ID | E4: Row Labels | F4: Sum of Total_Amount | I4: Sum of Total_Amount | J4: Column Labels
A5: 250 | E5: Appliances | F5: 0.036383132 | I5: Row Labels | J5: 2024 | K5: 2025 | L5: Grand Total
A6: Sum of Quantity | E6: Blender | F6: 0.022771821 | I6: Jan | K6: 25799.15 | L6: 25799.15
A7: 753 | E7: Coffee Maker | F7: 0.013611311 | I7: Feb | K7: 16069.38 | L7: 16069.38
A8: Row Labels | B8: Sum of Total_Amount | E8: Electronics | F8: 0.74939657 | I8: Mar | K8: 19899.38 | L8: 19899.38
A9: 2024 | B9: 160444.73 | E9: Headphones | F9: 0.030758122 | I9: Apr | J9: 20919.33 | K9: 6979.83 | L9: 27899.16
A10: 2025 | B10: 68747.74 | E10: Keyboard | F10: 0.034944909 | I10: May | J10: 17039.35 | L10: 17039.35
A11: Grand Total | B11: 229192.47 | E11: Laptop | F11: 0.29450902 | I11: Jun | J11: 19299.45 | L11: 19299.45
A12: Row Labels | B12: Sum of Total_Amount | E12: Monitor | F12: 0.095985352 | I12: Jul | J12: 18479.4 | L12: 18479.4
A13: 2024 | E13: Smartphone | F13: 0.29319916 | I13: Aug | J13: 15759.43 | L13: 15759.43
A14: 2025 | B14: -0.57151762 | E14: Furniture | F14: 0.2142203 | I14: Sep | J14: 12989.51 | L14: 12989.51
A15: Grand Total | E15: Bookshelf | F15: 0.066751669 | I15: Oct | J15: 20609.52 | L15: 20609.52
A16: Row Labels | B16: Sum of Total_Amount | E16: Desk | F16: 0.10209419 | I16: Nov | J16: 12309.44 | L16: 12309.44
A17: Central | B17: 41288.34 | E17: Office Chair | F17: 0.04537444 | I17: Dec | J17: 23039.3 | L17: 23039.3
A18: East | B18: 59288.39 | E18: Grand Total | F18: 1 | I18: Grand Total | J18: 160444.73 | K18: 68747.74 | L18: 229192.47
A19: North | B19: 50808.31
A20: South | B20: 36398.75
A21: West | B21: 41408.68
A22: Grand Total | B22: 229192.47

Sheet Row_Data
A1: Transaction_ID | B1: Date | C1: Customer_ID | D1: Customer_Name | E1: Product_ID | F1: Product_Name | G1: Category | H1: Quantity | I1: Unit_Price | J1: Payment_Method | K1: Region | L1: Customer_Segment | M1: Customer_Since | N1: Total_Amount | T1: {=_xlfn._xlws.FILTER(#REF!,#REF!="Top 10%")} -> #REF!
A2: TRX0155 | B2: 45393 | C2: CUST023 | D2: Paul Baker | E2: P009 | F2: Monitor | G2: Electronics | H2: 3 | I2: 249.99 | J2: Cash | K2: Central | L2: Basic | M2: 44425 | N2: 749.97
A3: TRX0023 | B3: 45396 | C3: CUST013 | D3: Joseph Jackson | E3: P009 | F3: Monitor | G3: Electronics | H3: 3 | I3: 249.99 | J3: Credit Card | K3: Central | L3: Premium | M3: 44575 | N3: 749.97
A4: TRX0139 | B4: 45399 | C4: CUST021 | D4: Kevin Scott | E4: P005 | F4: Blender | G4: Appliances | H4: 3 | I4: 59.99 | J4: PayPal | K4: South | L4: Standard | M4: 45262 | N4: 179.97
A5: TRX0043 | B5: 45400 | C5: CUST046 | D5: Kathleen Bennett | E5: P005 | F5: Blender | G5: Appliances | H5: 3 | I5: 59.99 | J5: Cash | K5: North | L5: Premium | M5: 45114 | N5: 179.97
A6: TRX0212 | B6: 45400 | C6: CUST003 | D6: Michael Brown | E6: P008 | F6: Bookshelf | G6: Furniture | H6: 5 | I6: 149.99 | J6: Credit Card | K6: North | L6: Premium | M6: 45295 | N6: 749.95
A7: TRX0092 | B7: 45403 | C7: CUST024 | D7: Dorothy Nelson | E7: P005 | F7: Blender | G7: Appliances | H7: 2 | I7: 59.99 | J7: Credit Card | K7: West | L7: Standard | M7: 44746 | N7: 119.98
A8: TRX0193 | B8: 45403 | C8: CUST024 | D8: Dorothy Nelson | E8: P003 | F8: Headphones | G8: Electronics | H8: 5 | I8: 149.99 | J8: Credit Card | K8: Central | L8: Standard | M8: 44418 | N8: 749.95
A9: TRX0240 | B9: 45403 | C9: CUST017 | D9: Charles Allen | E9: P005 | F9: Blender | G9: Appliances | H9: 3 | I9: 59.99 | J9: Debit Card | K9: South | L9: Basic | M9: 45007 | N9: 179.97
A10: TRX0135 | B10: 45405 | C10: CUST009 | D10: Robert Thomas | E10: P001 | F10: Laptop | G10: Electronics | H10: 3 | I10: 899.99 | J10: PayPal | K10: East | L10: Standard | M10: 45299 | N10: 2699.97
A11: TRX0185 | B11: 45408 | C11: CUST026 | D11: Karen Hill | E11: P005 | F11: Blender | G11: Appliances | H11: 3 | I11: 59.99 | J11: Cash | K11: West | L11: Premium | M11: 45207 | N11: 179.97
A12: TRX0138 | B12: 45408 | C12: CUST022 | D12: Susan Green | E12: P008 | F12: Bookshelf | G12: Furniture | H12: 1 | I12: 149.99 | J12: Credit Card | K12: West | L12: Standard | M12: 45103 | N12: 149.99
A13: TRX0209 | B13: 45408 | C13: CUST046 | D13: Kathleen Bennett | E13: P008 | F13: Bookshelf | G13: Furniture | H13: 5 | I13: 149.99 | J13: Debit Card | K13: North | L13: Basic | M13: 44830 | N13: 749.95
... A251: TRX0064 | B251: 45758 | C251: CUST031 | D251: Steven Turner | E251: P010 | F251: Keyboard | G251: Electronics | H251: 3 | I251: 89.99 | J251: Debit Card | K251: North | L251: Premium | M251: 44878 | N251: 269.97

Sheet Data_cleaning
A1: Transaction_ID | B1: Date | C1: month | D1: year | E1: date_year | F1: Customer_ID | G1: Customer_Name | H1: customer sort name | I1: Product_ID | J1: Product_Name | K1: Category | L1: Quantity | M1: Unit_Price | N1: Payment_Method | O1: Region | P1: region Code | Q1: Customer_Segment | R1: Customer_Since | S1: Total_Amount | T1: Today_Date | U1: current_Timestamp | V1: Order_Age_Days | W1: Month_End_Date | X1: created_Timestamp | Z1: filter
A2: TRX0155 | B2: 45393 | C2: =TEXT(Table1[[#This Row],[Date]],"mmm") -> Apr | D2: =YEAR(Table1[[#This Row],[Date]]) -> 2024 | E2: =TEXT(Table1[[#This Row],[Date]],"mmm-yyyy") -> Apr-2024 | F2: CUST023 | G2: Paul Baker | H2: =LEFT(Table1[[#This Row],[Customer_Name]],1)&LEFT(MID(Table1[[#This Row],[Customer_Name]],FIND(" ",Table1[[#This Row],[Customer_Name]])+1,50),1) -> PB | I2: P009 | J2: Monitor | K2: Electronics | L2: 3 | M2: 249.99 | N2: Cash | O2: Central | P2: =UPPER(LEFT(Table1[[#This Row],[Region]],2)) -> CE | Q2: Basic | R2: 44425 | S2: 749.97 | T2: =TODAY() -> 46057 | U2: =NOW() -> 46057.596 | V2: =DATEDIF(Table1[[#This Row],[Date]],TODAY(),"d") -> 664 | W2: =EOMONTH(Table1[[#This Row],[Date]],0) -> 45412 | X2: =IF($A2="", "", IF(X2=0, NOW(), X2)) -> 46040.623 | Z2: Transaction_ID | AA2: Date | AB2: Customer_ID | AC2: Customer_Name | AD2: Product_ID | AE2: Product_Name | AF2: Category | AG2: Quantity | AH2: Unit_Price | AI2: Payment_Method | AJ2: Region | AK2: Customer_Segment | AL2: Customer_Since | AM2: Total_Amount | AN2: Today_Date | AO2: current_Timestamp | AP2: Order_Age_Days | AQ2: Month_End_Date | AR2: created_Timestamp
A3: TRX0023 | B3: 45396 | C3: =TEXT(Table1[[#This Row],[Date]],"mmm") -> Apr | D3: =YEAR(Table1[[#This Row],[Date]]) -> 2024 | E3: =TEXT(Table1[[#This Row],[Date]],"mmm-yyyy") -> Apr-2024 | F3: CUST013 | G3: Joseph Jackson | H3: =LEFT(Table1[[#This Row],[Customer_Name]],1)&LEFT(MID(Table1[[#This Row],[Customer_Name]],FIND(" ",Table1[[#This Row],[Customer_Name]])+1,50),1) -> JJ | I3: P009 | J3: Monitor | K3: Electronics | L3: 3 | M3: 249.99 | N3: Credit Card | O3: Central | P3: =UPPER(LEFT(Table1[[#This Row],[Region]],2)) -> CE | Q3: Premium | R3: 44575 | S3: 749.97 | T3: =TODAY() -> 46057 | U3: =NOW() -> 46057.596 | V3: =DATEDIF(Table1[[#This Row],[Date]],TODAY(),"d") -> 661 | W3: =EOMONTH(Table1[[#This Row],[Date]],0) -> 45412 | X3: =IF($A3="", "", IF(X3=0, NOW(), X3)) -> 46040.623 | Z3: {=_xlfn._xlws.FILTER(Table1[],(Table1[Region]="West")*(Table1[Total_Amount]>AVERAGE(Table1[Total_Amount])))} -> TRX0191 | AA3: 45409 | AB3: Apr | AC3: 2024 | AD3: Apr-2024 | AE3: CUST038 | AF3: Michelle Rogers | AG3: MR | AH3: P002 | AI3: Smartphone | AJ3: Electronics | AK3: 3 | AL3: 699.99 | AM3: Credit Card | AN3: West | AO3: WE | AP3: Basic | AQ3: 44577 | AR3: 2099.97 | AS3: 46057 | AT3: 46057.596 | AU3: 648 | AV3: 45412 | AW3: 46040.623
A4: TRX0139 | B4: 45399 | C4: =TEXT(Table1[[#This Row],[Date]],"mmm") -> Apr | D4: =YEAR(Table1[[#This Row],[Date]]) -> 2024 | E4: =TEXT(Table1[[#This Row],[Date]],"mmm-yyyy") -> Apr-2024 | F4: CUST021 | G4: Kevin Scott | H4: =LEFT(Table1[[#This Row],[Customer_Name]],1)&LEFT(MID(Table1[[#This Row],[Customer_Name]],FIND(" ",Table1[[#This Row],[Customer_Name]])+1,50),1) -> KS | I4: P005 | J4: Blender | K4: Appliances | L4: 3 | M4: 59.99 | N4: PayPal | O4: South | P4: =UPPER(LEFT(Table1[[#This Row],[Region]],2)) -> SO | Q4: Standard | R4: 45262 | S4: 179.97 | T4: =TODAY() -> 46057 | U4: =NOW() -> 46057.596 | V4: =DATEDIF(Table1[[#This Row],[Date]],TODAY(),"d") -> 658 | W4: =EOMONTH(Table1[[#This Row],[Date]],0) -> 45412 | X4: =IF($A4="", "", IF(X4=0, NOW(), X4)) -> 46040.623 | Z4: TRX0122 | AA4: 45410 | AB4: Apr | AC4: 2024 | AD4: Apr-2024 | AE4: CUST025 | AF4: Mark Carter | AG4: MC | AH4: P001 | AI4: Laptop | AJ4: Electronics | AK4: 4 | AL4: 899.99 | AM4: Credit Card | AN4: West | AO4: WE | AP4: Standard | AQ4: 45327 | AR4: 3599.96 | AS4: 46057 | AT4: 46057.596 | AU4: 647 | AV4: 45412 | AW4: 46040.623
A5: TRX0043 | B5: 45400 | C5: =TEXT(Table1[[#This Row],[Date]],"mmm") -> Apr | D5: =YEAR(Table1[[#This Row],[Date]]) -> 2024 | E5: =TEXT(Table1[[#This Row],[Date]],"mmm-yyyy") -> Apr-2024 | F5: CUST046 | G5: Kathleen Bennett | H5: =LEFT(Table1[[#This Row],[Customer_Name]],1)&LEFT(MID(Table1[[#This Row],[Customer_Name]],FIND(" ",Table1[[#This Row],[Customer_Name]])+1,50),1) -> KB | I5: P005 | J5: Blender | K5: Appliances | L5: 3 | M5: 59.99 | N5: Cash | O5: North | P5: =UPPER(LEFT(Table1[[#This Row],[Region]],2)) -> NO | Q5: Premium | R5: 45114 | S5: 179.97 | T5: =TODAY() -> 46057 | U5: =NOW() -> 46057.596 | V5: =DATEDIF(Table1[[#This Row],[Date]],TODAY(),"d") -> 657 | W5: =EOMONTH(Table1[[#This Row],[Date]],0) -> 45412 | X5: =IF($A5="", "", IF(X5=0, NOW(), X5)) -> 46040.623 | Z5: TRX0231 | AA5: 45412 | AB5: Apr | AC5: 2024 | AD5: Apr-2024 | AE5: CUST018 | AF5: Barbara Young | AG5: BY | AH5: P002 | AI5: Smartphone | AJ5: Electronics | AK5: 5 | AL5: 699.99 | AM5: Cash | AN5: West | AO5: WE | AP5: Basic | AQ5: 45167 | AR5: 3499.95 | AS5: 46057 | AT5: 46057.596 | AU5: 645 | AV5: 45412 | AW5: 46040.623
A6: TRX0212 | B6: 45400 | C6: =TEXT(Table1[[#This Row],[Date]],"mmm") -> Apr | D6: =YEAR(Table1[[#This Row],[Date]]) -> 2024 | E6: =TEXT(Table1[[#This Row],[Date]],"mmm-yyyy") -> Apr-2024 | F6: CUST003 | G6: Michael Brown | H6: =LEFT(Table1[[#This Row],[Customer_Name]],1)&LEFT(MID(Table1[[#This Row],[Customer_Name]],FIND(" ",Table1[[#This Row],[Customer_Name]])+1,50),1) -> MB | I6: P008 | J6: Bookshelf | K6: Furniture | L6: 5 | M6: 149.99 | N6: Credit Card | O6: North | P6: =UPPER(LEFT(Table1[[#This Row],[Region]],2)) -> NO | Q6: Premium | R6: 45295 | S6: 749.95 | T6: =TODAY() -> 46057 | U6: =NOW() -> 46057.596 | V6: =DATEDIF(Table1[[#This Row],[Date]],TODAY(),"d") -> 657 | W6: =EOMONTH(Table1[[#This Row],[Date]],0) -> 45412 | X6: =IF($A6="", "", IF(X6=0, NOW(), X6)) -> 46040.623 | Z6: TRX0242 | AA6: 45416 | AB6: May | AC6: 2024 | AD6: May-2024 | AE6: CUST025 | AF6: Mark Carter | AG6: MC | AH6: P007 | AI6: Desk | AJ6: Furniture | AK6: 4 | AL6: 299.99 | AM6: Cash | AN6: West | AO6: WE | AP6: Premium | AQ6: 44716 | AR6: 1199.96 | AS6: 46057 | AT6: 46057.596 | AU6: 641 | AV6: 45443 | AW6: 46040.623
A7: TRX0092 | B7: 45403 | C7: =TEXT(Table1[[#This Row],[Date]],"mmm") -> Apr | D7: =YEAR(Table1[[#This Row],[Date]]) -> 2024 | E7: =TEXT(Table1[[#This Row],[Date]],"mmm-yyyy") -> Apr-2024 | F7: CUST024 | G7: Dorothy Nelson | H7: =LEFT(Table1[[#This Row],[Customer_Name]],1)&LEFT(MID(Table1[[#This Row],[Customer_Name]],FIND(" ",Table1[[#This Row],[Customer_Name]])+1,50),1) -> DN | I7: P005 | J7: Blender | K7: Appliances | L7: 2 | M7: 59.99 | N7: Cash | O7: West | P7: =UPPER(LEFT(Table1[[#This Row],[Region]],2)) -> WE | Q7: Standard | R7: 44746 | S7: 119.98 | T7: =TODAY() -> 46057 | U7: =NOW() -> 46057.596 | V7: =DATEDIF(Table1[[#This Row],[Date]],TODAY(),"d") -> 654 | W7: =EOMONTH(Table1[[#This Row],[Date]],0) -> 45412 | X7: =IF($A7="", "", IF(X7=0, NOW(), X7)) -> 46040.623 | Z7: TRX0071 | AA7: 45422 | AB7: May | AC7: 2024 | AD7: May-2024 | AE7: CUST036 | AF7: Nancy Collins | AG7: NC | AH7: P009 | AI7: Monitor | AJ7: Electronics | AK7: 5 | AL7: 249.99 | AM7: Credit Card | AN7: West | AO7: WE | AP7: Standard | AQ7: 44525 | AR7: 1249.95 | AS7: 46057 | AT7: 46057.596 | AU7: 635 | AV7: 45443 | AW7: 46040.623
A8: TRX0193 | B8: 45403 | C8: =TEXT(Table1[[#This Row],[Date]],"mmm") -> Apr | D8: =YEAR(Table1[[#This Row],[Date]]) -> 2024 | E8: =TEXT(Table1[[#This Row],[Date]],"mmm-yyyy") -> Apr-2024 | F8: CUST024 | G8: Dorothy Nelson | H8: =LEFT(Table1[[#This Row],[Customer_Name]],1)&LEFT(MID(Table1[[#This Row],[Customer_Name]],FIND(" ",Table1[[#This Row],[Customer_Name]])+1,50),1) -> DN | I8: P003 | J8: Headphones | K8: Electronics | L8: 5 | M8: 149.99 | N8: Credit Card | O8: Central | P8: =UPPER(LEFT(Table1[[#This Row],[Region]],2)) -> CE | Q8: Standard | R8: 44418 | S8: 749.95 | T8: =TODAY() -> 46057 | U8: =NOW() -> 46057.596 | V8: =DATEDIF(Table1[[#This Row],[Date]],TODAY(),"d") -> 654 | W8: =EOMONTH(Table1[[#This Row],[Date]],0) -> 45412 | X8: =IF($A8="", "", IF(X8=0, NOW(), X8)) -> 46040.623 | Z8: TRX0015 | AA8: 45440 | AB8: May | AC8: 2024 | AD8: May-2024 | AE8: CUST008 | AF8: Jennifer Taylor | AG8: JT | AH8: P002 | AI8: Smartphone | AJ8: Electronics | AK8: 5 | AL8: 699.99 | AM8: PayPal | AN8: West | AO8: WE | AP8: Standard | AQ8: 44407 | AR8: 3499.95 | AS8: 46057 | AT8: 46057.596 | AU8: 617 | AV8: 45443 | AW8: 46040.623
A9: TRX0240 | B9: 45403 | C9: =TEXT(Table1[[#This Row],[Date]],"mmm") -> Apr | D9: =YEAR(Table1[[#This Row],[Date]]) -> 2024 | E9: =TEXT(Table1[[#This Row],[Date]],"mmm-yyyy") -> Apr-2024 | F9: CUST017 | G9: Charles Allen | H9: =LEFT(Table1[[#This Row],[Customer_Name]],1)&LEFT(MID(Table1[[#This Row],[Customer_Name]],FIND(" ",Table1[[#This Row],[Customer_Name]])+1,50),1) -> CA | I9: P005 | J9: Blender | K9: Appliances | L9: 3 | M9: 59.99 | N9: Debit Card | O9: South | P9: =UPPER(LEFT(Table1[[#This Row],[Region]],2)) -> SO | Q9: Basic | R9: 45007 | S9: 179.97 | T9: =TODAY() -> 46057 | U9: =NOW() -> 46057.596 | V9: =DATEDIF(Table1[[#This Row],[Date]],TODAY(),"d") -> 654 | W9: =EOMONTH(Table1[[#This Row],[Date]],0) -> 45412 | X9: =IF($A9="", "", IF(X9=0, NOW(), X9)) -> 46040.623 | Z9: TRX0158 | AA9: 45579 | AB9: Oct | AC9: 2024 | AD9: Oct-2024 | AE9: CUST027 | AF9: George Adams | AG9: GA | AH9: P001 | AI9: Laptop | AJ9: Electronics | AK9: 3 | AL9: 899.99 | AM9: PayPal | AN9: West | AO9: WE | AP9: Basic | AQ9: 45215 | AR9: 2699.97 | AS9: 46057 | AT9: 46057.596 | AU9: 478 | AV9: 45596 | AW9: 46040.623
A10: TRX0135 | B10: 45405 | C10: =TEXT(Table1[[#This Row],[Date]],"mmm") -> Apr | D10: =YEAR(Table1[[#This Row],[Date]]) -> 2024 | E10: =TEXT(Table1[[#This Row],[Date]],"mmm-yyyy") -> Apr-2024 | F10: CUST009 | G10: Robert Thomas | H10: =LEFT(Table1[[#This Row],[Customer_Name]],1)&LEFT(MID(Table1[[#This Row],[Customer_Name]],FIND(" ",Table1[[#This Row],[Customer_Name]])+1,50),1) -> RT | I10: P001 | J10: Laptop | K10: Electronics | L10: 3 | M10: 899.99 | N10: PayPal | O10: East | P10: =UPPER(LEFT(Table1[[#This Row],[Region]],2)) -> EA | Q10: Standard | R10: 45299 | S10: 2699.97 | T10: =TODAY() -> 46057 | U10: =NOW() -> 46057.596 | V10: =DATEDIF(Table1[[#This Row],[Date]],TODAY(),"d") -> 652 | W10: =EOMONTH(Table1[[#This Row],[Date]],0) -> 45412 | X10: =IF($A10="", "", IF(X10=0, NOW(), X10)) -> 46040.623 | Z10: TRX0076 | AA10: 45607 | AB10: Nov | AC10: 2024 | AD10: Nov-2024 | AE10: CUST012 | AF10: Patricia Moore | AG10: PM | AH10: P009 | AI10: Monitor | AJ10: Electronics | AK10: 4 | AL10: 249.99 | AM10: Credit Card | AN10: West | AO10: WE | AP10: Standard | AQ10: 44659 | AR10: 999.96 | AS10: 46057 | AT10: 46057.596 | AU10: 450 | AV10: 45626 | AW10: 46040.623
A11: TRX0185 | B11: 45408 | C11: =TEXT(Table1[[#This Row],[Date]],"mmm") -> Apr | D11: =YEAR(Table1[[#This Row],[Date]]) -> 2024 | E11: =TEXT(Table1[[#This Row],[Date]],"mmm-yyyy") -> Apr-2024 | F11: CUST026 | G11: Karen Hill | H11: =LEFT(Table1[[#This Row],[Customer_Name]],1)&LEFT(MID(Table1[[#This Row],[Customer_Name]],FIND(" ",Table1[[#This Row],[Customer_Name]])+1,50),1) -> KH | I11: P005 | J11: Blender | K11: Appliances | L11: 3 | M11: 59.99 | N11: Cash | O11: West | P11: =UPPER(LEFT(Table1[[#This Row],[Region]],2)) -> WE | Q11: Premium | R11: 45207 | S11: 179.97 | T11: =TODAY() -> 46057 | U11: =NOW() -> 46057.596 | V11: =DATEDIF(Table1[[#This Row],[Date]],TODAY(),"d") -> 649 | W11: =EOMONTH(Table1[[#This Row],[Date]],0) -> 45412 | X11: =IF($A11="", "", IF(X11=0, NOW(), X11)) -> 46040.623 | Z11: TRX0033 | AA11: 45613 | AB11: Nov | AC11: 2024 | AD11: Nov-2024 | AE11: CUST025 | AF11: Mark Carter | AG11: MC | AH11: P002 | AI11: Smartphone | AJ11: Electronics | AK11: 2 | AL11: 699.99 | AM11: PayPal | AN11: West | AO11: WE | AP11: Standard | AQ11: 44770 | AR11: 1399.98 | AS11: 46057 | AT11: 46057.596 | AU11: 444 | AV11: 45626 | AW11: 46040.623
A12: TRX0138 | B12: 45408 | C12: =TEXT(Table1[[#This Row],[Date]],"mmm") -> Apr | D12: =YEAR(Table1[[#This Row],[Date]]) -> 2024 | E12: =TEXT(Table1[[#This Row],[Date]],"mmm-yyyy") -> Apr-2024 | F12: CUST022 | G12: Susan Green | H12: =LEFT(Table1[[#This Row],[Customer_Name]],1)&LEFT(MID(Table1[[#This Row],[Customer_Name]],FIND(" ",Table1[[#This Row],[Customer_Name]])+1,50),1) -> SG | I12: P008 | J12: Bookshelf | K12: Furniture | L12: 1 | M12: 149.99 | N12: Credit Card | O12: West | P12: =UPPER(LEFT(Table1[[#This Row],[Region]],2)) -> WE | Q12: Standard | R12: 45103 | S12: 149.99 | T12: =TODAY() -> 46057 | U12: =NOW() -> 46057.596 | V12: =DATEDIF(Table1[[#This Row],[Date]],TODAY(),"d") -> 649 | W12: =EOMONTH(Table1[[#This Row],[Date]],0) -> 45412 | X12: =IF($A12="", "", IF(X12=0, NOW(), X12)) -> 46040.623 | Z12: TRX0148 | AA12: 45619 | AB12: Nov | AC12: 2024 | AD12: Nov-2024 | AE12: CUST004 | AF12: Sarah Davis | AG12: SD | AH12: P002 | AI12: Smartphone | AJ12: Electronics | AK12: 3 | AL12: 699.99 | AM12: PayPal | AN12: West | AO12: WE | AP12: Standard | AQ12: 44583 | AR12: 2099.97 | AS12: 46057 | AT12: 46057.596 | AU12: 438 | AV12: 45626 | AW12: 46040.623
A13: TRX0209 | B13: 45408 | C13: =TEXT(Table1[[#This Row],[Date]],"mmm") -> Apr | D13: =YEAR(Table1[[#This Row],[Date]]) -> 2024 | E13: =TEXT(Table1[[#This Row],[Date]],"mmm-yyyy") -> Apr-2024 | F13: CUST046 | G13: Kathleen Bennett | H13: =LEFT(Table1[[#This Row],[Customer_Name]],1)&LEFT(MID(Table1[[#This Row],[Customer_Name]],FIND(" ",Table1[[#This Row],[Customer_Name]])+1,50),1) -> KB | I13: P008 | J13: Bookshelf | K13: Furniture | L13: 5 | M13: 149.99 | N13: Debit Card | O13: North | P13: =UPPER(LEFT(Table1[[#This Row],[Region]],2)) -> NO | Q13: Basic | R13: 44830 | S13: 749.95 | T13: =TODAY() -> 46057 | U13: =NOW() -> 46057.596 | V13: =DATEDIF(Table1[[#This Row],[Date]],TODAY(),"d") -> 649 | W13: =EOMONTH(Table1[[#This Row],[Date]],0) -> 45412 | X13: =IF($A13="", "", IF(X13=0, NOW(), X13)) -> 46040.623 | Z13: TRX0201 | AA13: 45627 | AB13: Dec | AC13: 2024 | AD13: Dec-2024 | AE13: CUST025 | AF13: Mark Carter | AG13: MC | AH13: P002 | AI13: Smartphone | AJ13: Electronics | AK13: 5 | AL13: 699.99 | AM13: Debit Card | AN13: West | AO13: WE | AP13: Standard | AQ13: 44944 | AR13: 3499.95 | AS13: 46057 | AT13: 46057.596 | AU13: 430 | AV13: 45657 | AW13: 46040.623
A14: TRX0246 | B14: 45408 | C14: =TEXT(Table1[[#This Row],[Date]],"mmm") -> Apr | D14: =YEAR(Table1[[#This Row],[Date]]) -> 2024 | E14: =TEXT(Table1[[#This Row],[Date]],"mmm-yyyy") -> Apr-2024 | F14: CUST041 | G14: Peter Richardson | H14: =LEFT(Table1[[#This Row],[Customer_Name]],1)&LEFT(MID(Table1[[#This Row],[Customer_Name]],FIND(" ",Table1[[#This Row],[Customer_Name]])+1,50),1) -> PR | I14: P008 | J14: Bookshelf | K14: Furniture | L14: 3 | M14: 149.99 | N14: Cash | O14: North | P14: =UPPER(LEFT(Table1[[#This Row],[Region]],2)) -> NO | Q14: Premium | R14: 44806 | S14: 449.97 | T14: =TODAY() -> 46057 | U14: =NOW() -> 46057.596 | V14: =DATEDIF(Table1[[#This Row],[Date]],TODAY(),"d") -> 649 | W14: =EOMONTH(Table1[[#This Row],[Date]],0) -> 45412 | X14: =IF($A14="", "", IF(X14=0, NOW(), X14)) -> 46040.623 | Z14: TRX0010 | AA14: 45688 | AB14: Jan | AC14: 2025 | AD14: Jan-2025 | AE14: CUST026 | AF14: Karen Hill | AG14: KH | AH14: P002 | AI14: Smartphone | AJ14: Electronics | AK14: 4 | AL14: 699.99 | AM14: Debit Card | AN14: West | AO14: WE | AP14: Premium | AQ14: 44692 | AR14: 2799.96 | AS14: 46057 | AT14: 46057.596 | AU14: 369 | AV14: 45688 | AW14: 46040.623
A15: TRX0067 | B15: 45409 | C15: =TEXT(Table1[[#This Row],[Date]],"mmm") -> Apr | D15: =YEAR(Table1[[#This Row],[Date]]) -> 2024 | E15: =TEXT(Table1[[#This Row],[Date]],"mmm-yyyy") -> Apr-2024 | F15: CUST043 | G15: Dennis Gray | H15: =LEFT(Table1[[#This Row],[Customer_Name]],1)&LEFT(MID(Table1[[#This Row],[Customer_Name]],FIND(" ",Table1[[#This Row],[Customer_Name]])+1,50),1) -> DG | I15: P005 | J15: Blender | K15: Appliances | L15: 3 | M15: 59.99 | N15: Credit Card | O15: North | P15: =UPPER(LEFT(Table1[[#This Row],[Region]],2)) -> NO | Q15: Standard | R15: 45351 | S15: 179.97 | T15: =TODAY() -> 46057 | U15: =NOW() -> 46057.596 | V15: =DATEDIF(Table1[[#This Row],[Date]],TODAY(),"d") -> 648 | W15: =EOMONTH(Table1[[#This Row],[Date]],0) -> 45412 | X15: =IF($A15="", "", IF(X15=0, NOW(), X15)) -> 46040.623 | Z15: TRX0083 | AA15: 45710 | AB15: Feb | AC15: 2025 | AD15: Feb-2025 | AE15: CUST017 | AF15: Charles Allen | AG15: CA | AH15: P007 | AI15: Desk | AJ15: Furniture | AK15: 5 | AL15: 299.99 | AM15: Cash | AN15: West | AO15: WE | AP15: Standard | AQ15: 45142 | AR15: 1499.95 | AS15: 46057 | AT15: 46057.596 | AU15: 347 | AV15: 45716 | AW15: 46040.623
A16: TRX0191 | B16: 45409 | C16: =TEXT(Table1[[#This Row],[Date]],"mmm") -> Apr | D16: =YEAR(Table1[[#This Row],[Date]]) -> 2024 | E16: =TEXT(Table1[[#This Row],[Date]],"mmm-yyyy") -> Apr-2024 | F16: CUST038 | G16: Michelle Rogers | H16: =LEFT(Table1[[#This Row],[Customer_Name]],1)&LEFT(MID(Table1[[#This Row],[Customer_Name]],FIND(" ",Table1[[#This Row],[Customer_Name]])+1,50),1) -> MR | I16: P002 | J16: Smartphone | K16: Electronics | L16: 3 | M16: 699.99 | N16: Credit Card | O16: West | P16: =UPPER(LEFT(Table1[[#This Row],[Region]],2)) -> WE | Q16: Basic | R16: 44577 | S16: 2099.97 | T16: =TODAY() -> 46057 | U16: =NOW() -> 46057.596 | V16: =DATEDIF(Table1[[#This Row],[Date]],TODAY(),"d") -> 648 | W16: =EOMONTH(Table1[[#This Row],[Date]],0) -> 45412 | X16: =IF($A16="", "", IF(X16=0, NOW(), X16)) -> 46040.623
A17: TRX0230 | B17: 45409 | C17: =TEXT(Table1[[#This Row],[Date]],"mmm") -> Apr | D17: =YEAR(Table1[[#This Row],[Date]]) -> 2024 | E17: =TEXT(Table1[[#This Row],[Date]],"mmm-yyyy") -> Apr-2024 | F17: CUST027 | G17: George Adams | H17: =LEFT(Table1[[#This Row],[Customer_Name]],1)&LEFT(MID(Table1[[#This Row],[Customer_Name]],FIND(" ",Table1[[#This Row],[Customer_Name]])+1,50),1) -> GA | I17: P001 | J17: Laptop | K17: Electronics | L17: 1 | M17: 899.99 | N17: Debit Card | O17: North | P17: =UPPER(LEFT(Table1[[#This Row],[Region]],2)) -> NO | Q17: Standard | R17: 44920 | S17: 899.99 | T17: =TODAY() -> 46057 | U17: =NOW() -> 46057.596 | V17: =DATEDIF(Table1[[#This Row],[Date]],TODAY(),"d") -> 648 | W17: =EOMONTH(Table1[[#This Row],[Date]],0) -> 45412 | X17: =IF($A17="", "", IF(X17=0, NOW(), X17)) -> 46040.623
A18: TRX0049 | B18: 45410 | C18: =TEXT(Table1[[#This Row],[Date]],"mmm") -> Apr | D18: =YEAR(Table1[[#This Row],[Date]]) -> 2024 | E18: =TEXT(Table1[[#This Row],[Date]],"mmm-yyyy") -> Apr-2024 | F18: CUST025 | G18: Mark Carter | H18: =LEFT(Table1[[#This Row],[Customer_Name]],1)&LEFT(MID(Table1[[#This Row],[Customer_Name]],FIND(" ",Table1[[#This Row],[Customer_Name]])+1,50),1) -> MC | I18: P008 | J18: Bookshelf | K18: Furniture | L18: 4 | M18: 149.99 | N18: Debit Card | O18: North | P18: =UPPER(LEFT(Table1[[#This Row],[Region]],2)) -> NO | Q18: Premium | R18: 45374 | S18: 599.96 | T18: =TODAY() -> 46057 | U18: =NOW() -> 46057.596 | V18: =DATEDIF(Table1[[#This Row],[Date]],TODAY(),"d") -> 647 | W18: =EOMONTH(Table1[[#This Row],[Date]],0) -> 45412 | X18: =IF($A18="", "", IF(X18=0, NOW(), X18)) -> 46040.623
A19: TRX0134 | B19: 45410 | C19: =TEXT(Table1[[#This Row],[Date]],"mmm") -> Apr | D19: =YEAR(Table1[[#This Row],[Date]]) -> 2024 | E19: =TEXT(Table1[[#This Row],[Date]],"mmm-yyyy") -> Apr-2024 | F19: CUST010 | G19: Maria Garcia | H19: =LEFT(Table1[[#This Row],[Customer_Name]],1)&LEFT(MID(Table1[[#This Row],[Customer_Name]],FIND(" ",Table1[[#This Row],[Customer_Name]])+1,50),1) -> MG | I19: P002 | J19: Smartphone | K19: Electronics | L19: 2 | M19: 699.99 | N19: Cash | O19: North | P19: =UPPER(LEFT(Table1[[#This Row],[Region]],2)) -> NO | Q19: Basic | R19: 44781 | S19: 1399.98 | T19: =TODAY() -> 46057 | U19: =NOW() -> 46057.596 | V19: =DATEDIF(Table1[[#This Row],[Date]],TODAY(),"d") -> 647 | W19: =EOMONTH(Table1[[#This Row],[Date]],0) -> 45412 | X19: =IF($A19="", "", IF(X19=0, NOW(), X19)) -> 46040.623
A20: TRX0122 | B20: 45410 | C20: =TEXT(Table1[[#This Row],[Date]],"mmm") -> Apr | D20: =YEAR(Table1[[#This Row],[Date]]) -> 2024 | E20: =TEXT(Table1[[#This Row],[Date]],"mmm-yyyy") -> Apr-2024 | F20: CUST025 | G20: Mark Carter | H20: =LEFT(Table1[[#This Row],[Customer_Name]],1)&LEFT(MID(Table1[[#This Row],[Customer_Name]],FIND(" ",Table1[[#This Row],[Customer_Name]])+1,50),1) -> MC | I20: P001 | J20: Laptop | K20: Electronics | L20: 4 | M20: 899.99 | N20: Credit Card | O20: West | P20: =UPPER(LEFT(Table1[[#This Row],[Region]],2)) -> WE | Q20: Standard | R20: 45327 | S20: 3599.96 | T20: =TODAY() -> 46057 | U20: =NOW() -> 46057.596 | V20: =DATEDIF(Table1[[#This Row],[Date]],TODAY(),"d") -> 647 | W20: =EOMONTH(Table1[[#This Row],[Date]],0) -> 45412 | X20: =IF($A20="", "", IF(X20=0, NOW(), X20)) -> 46040.623
A21: TRX0222 | B21: 45410 | C21: =TEXT(Table1[[#This Row],[Date]],"mmm") -> Apr | D21: =YEAR(Table1[[#This Row],[Date]]) -> 2024 | E21: =TEXT(Table1[[#This Row],[Date]],"mmm-yyyy") -> Apr-2024 | F21: CUST048 | G21: Virginia Sanders | H21: =LEFT(Table1[[#This Row],[Customer_Name]],1)&LEFT(MID(Table1[[#This Row],[Customer_Name]],FIND(" ",Table1[[#This Row],[Customer_Name]])+1,50),1) -> VS | I21: P009 | J21: Monitor | K21: Electronics | L21: 3 | M21: 249.99 | N21: Credit Card | O21: North | P21: =UPPER(LEFT(Table1[[#This Row],[Region]],2)) -> NO | Q21: Premium | R21: 45224 | S21: 749.97 | T21: =TODAY() -> 46057 | U21: =NOW() -> 46057.596 | V21: =DATEDIF(Table1[[#This Row],[Date]],TODAY(),"d") -> 647 | W21: =EOMONTH(Table1[[#This Row],[Date]],0) -> 45412 | X21: =IF($A21="", "", IF(X21=0, NOW(), X21)) -> 46040.623
A22: TRX0231 | B22: 45412 | C22: =TEXT(Table1[[#This Row],[Date]],"mmm") -> Apr | D22: =YEAR(Table1[[#This Row],[Date]]) -> 2024 | E22: =TEXT(Table1[[#This Row],[Date]],"mmm-yyyy") -> Apr-2024 | F22: CUST018 | G22: Barbara Young | H22: =LEFT(Table1[[#This Row],[Customer_Name]],1)&LEFT(MID(Table1[[#This Row],[Customer_Name]],FIND(" ",Table1[[#This Row],[Customer_Name]])+1,50),1) -> BY | I22: P002 | J22: Smartphone | K22: Electronics | L22: 5 | M22: 699.99 | N22: Cash | O22: West | P22: =UPPER(LEFT(Table1[[#This Row],[Region]],2)) -> WE | Q22: Basic | R22: 45167 | S22: 3499.95 | T22: =TODAY() -> 46057 | U22: =NOW() -> 46057.596 | V22: =DATEDIF(Table1[[#This Row],[Date]],TODAY(),"d") -> 645 | W22: =EOMONTH(Table1[[#This Row],[Date]],0) -> 45412 | X22: =IF($A22="", "", IF(X22=0, NOW(), X22)) -> 46040.623
A23: TRX0239 | B23: 45413 | C23: =TEXT(Table1[[#This Row],[Date]],"mmm") -> May | D23: =YEAR(Table1[[#This Row],[Date]]) -> 2024 | E23: =TEXT(Table1[[#This Row],[Date]],"mmm-yyyy") -> May-2024 | F23: CUST012 | G23: Patricia Moore | H23: =LEFT(Table1[[#This Row],[Customer_Name]],1)&LEFT(MID(Table1[[#This Row],[Customer_Name]],FIND(" ",Table1[[#This Row],[Customer_Name]])+1,50),1) -> PM | I23: P002 | J23: Smartphone | K23: Electronics | L23: 4 | M23: 699.99 | N23: Cash | O23: East | P23: =UPPER(LEFT(Table1[[#This Row],[Region]],2)) -> EA | Q23: Standard | R23: 44409 | S23: 2799.96 | T23: =TODAY() -> 46057 | U23: =NOW() -> 46057.596 | V23: =DATEDIF(Table1[[#This Row],[Date]],TODAY(),"d") -> 644 | W23: =EOMONTH(Table1[[#This Row],[Date]],0) -> 45443 | X23: =IF($A23="", "", IF(X23=0, NOW(), X23)) -> 46040.623
A24: TRX0204 | B24: 45415 | C24: =TEXT(Table1[[#This Row],[Date]],"mmm") -> May | D24: =YEAR(Table1[[#This Row],[Date]]) -> 2024 | E24: =TEXT(Table1[[#This Row],[Date]],"mmm-yyyy") -> May-2024 | F24: CUST044 | G24: Cynthia Price | H24: =LEFT(Table1[[#This Row],[Customer_Name]],1)&LEFT(MID(Table1[[#This Row],[Customer_Name]],FIND(" ",Table1[[#This Row],[Customer_Name]])+1,50),1) -> CP | I24: P009 | J24: Monitor | K24: Electronics | L24: 4 | M24: 249.99 | N24: PayPal | O24: North | P24: =UPPER(LEFT(Table1[[#This Row],[Region]],2)) -> NO | Q24: Standard | R24: 44468 | S24: 999.96 | T24: =TODAY() -> 46057 | U24: =NOW() -> 46057.596 | V24: =DATEDIF(Table1[[#This Row],[Date]],TODAY(),"d") -> 642 | W24: =EOMONTH(Table1[[#This Row],[Date]],0) -> 45443 | X24: =IF($A24="", "", IF(X24=0, NOW(), X24)) -> 46040.623
A25: TRX0242 | B25: 45416 | C25: =TEXT(Table1[[#This Row],[Date]],"mmm") -> May | D25: =YEAR(Table1[[#This Row],[Date]]) -> 2024 | E25: =TEXT(Table1[[#This Row],[Date]],"mmm-yyyy") -> May-2024 | F25: CUST025 | G25: Mark Carter | H25: =LEFT(Table1[[#This Row],[Customer_Name]],1)&LEFT(MID(Table1[[#This Row],[Customer_Name]],FIND(" ",Table1[[#This Row],[Customer_Name]])+1,50),1) -> MC | I25: P007 | J25: Desk | K25: Furniture | L25: 4 | M25: 299.99 | N25: Cash | O25: West | P25: =UPPER(LEFT(Table1[[#This Row],[Region]],2)) -> WE | Q25: Premium | R25: 44716 | S25: 1199.96 | T25: =TODAY() -> 46057 | U25: =NOW() -> 46057.596 | V25: =DATEDIF(Table1[[#This Row],[Date]],TODAY(),"d") -> 641 | W25: =EOMONTH(Table1[[#This Row],[Date]],0) -> 45443 | X25: =IF($A25="", "", IF(X25=0, NOW(), X25)) -> 46040.623
A26: TRX0071 | B26: 45422 | C26: =TEXT(Table1[[#This Row],[Date]],"mmm") -> May | D26: =YEAR(Table1[[#This Row],[Date]]) -> 2024 | E26: =TEXT(Table1[[#This Row],[Date]],"mmm-yyyy") -> May-2024 | F26: CUST036 | G26: Nancy Collins | H26: =LEFT(Table1[[#This Row],[Customer_Name]],1)&LEFT(MID(Table1[[#This Row],[Customer_Name]],FIND(" ",Table1[[#This Row],[Customer_Name]])+1,50),1) -> NC | I26: P009 | J26: Monitor | K26: Electronics | L26: 5 | M26: 249.99 | N26: Credit Card | O26: West | P26: =UPPER(LEFT(Table1[[#This Row],[Region]],2)) -> WE | Q26: Standard | R26: 44525 | S26: 1249.95 | T26: =TODAY() -> 46057 | U26: =NOW() -> 46057.596 | V26: =DATEDIF(Table1[[#This Row],[Date]],TODAY(),"d") -> 635 | W26: =EOMONTH(Table1[[#This Row],[Date]],0) -> 45443 | X26: =IF($A26="", "", IF(X26=0, NOW(), X26)) -> 46040.623
A27: TRX0040 | B27: 45424 | C27: =TEXT(Table1[[#This Row],[Date]],"mmm") -> May | D27: =YEAR(Table1[[#This Row],[Date]]) -> 2024 | E27: =TEXT(Table1[[#This Row],[Date]],"mmm-yyyy") -> May-2024 | F27: CUST022 | G27: Susan Green | H27: =LEFT(Table1[[#This Row],[Customer_Name]],1)&LEFT(MID(Table1[[#This Row],[Customer_Name]],FIND(" ",Table1[[#This Row],[Customer_Name]])+1,50),1) -> SG | I27: P007 | J27: Desk | K27: Furniture | L27: 5 | M27: 299.99 | N27: PayPal | O27: East | P27: =UPPER(LEFT(Table1[[#This Row],[Region]],2)) -> EA | Q27: Basic | R27: 45168 | S27: 1499.95 | T27: =TODAY() -> 46057 | U27: =NOW() -> 46057.596 | V27: =DATEDIF(Table1[[#This Row],[Date]],TODAY(),"d") -> 633 | W27: =EOMONTH(Table1[[#This Row],[Date]],0) -> 45443 | X27: =IF($A27="", "", IF(X27=0, NOW(), X27)) -> 46040.623
... A251: TRX0064 | B251: 45758 | C251: =TEXT(Table1[[#This Row],[Date]],"mmm") -> Apr | D251: =YEAR(Table1[[#This Row],[Date]]) -> 2025 | E251: =TEXT(Table1[[#This Row],[Date]],"mmm-yyyy") -> Apr-2025 | F251: CUST031 | G251: Steven Turner | H251: =LEFT(Table1[[#This Row],[Customer_Name]],1)&LEFT(MID(Table1[[#This Row],[Customer_Name]],FIND(" ",Table1[[#This Row],[Customer_Name]])+1,50),1) -> ST | I251: P010 | J251: Keyboard | K251: Electronics | L251: 3 | M251: 89.99 | N251: Debit Card | O251: North | P251: =UPPER(LEFT(Table1[[#This Row],[Region]],2)) -> NO | Q251: Premium | R251: 44878 | S251: 269.97 | T251: =TODAY() -> 46057 | U251: =NOW() -> 46057.596 | V251: =DATEDIF(Table1[[#This Row],[Date]],TODAY(),"d") -> 299 | W251: =EOMONTH(Table1[[#This Row],[Date]],0) -> 45777 | X251: =IF($A251="", "", IF(X251=0, NOW(), X251)) -> 46040.623

Sheet groupby using formulas
A1: Customer_Name | B1: total sales per customer | D1: Product_Name | E1: total sales by product | G1: Customer_Name | H1: order_count | I1: Premium Customer | K1: Product_Name | L1: how many time purchased
A2: {=_xlfn.UNIQUE(Table1[Customer_Name])} -> Paul Baker | B2: =SUMIF(Table1[Customer_Name],'groupby using formulas'!A2,Table1[Total_Amount]) -> 8309.74 | D2: {=_xlfn.UNIQUE(Table1[Product_Name])} -> Monitor | E2: =SUMIF(Table1[Product_Name],D2,Table1[Total_Amount]) -> 21999.12 | G2: {=_xlfn.UNIQUE(Table1[Customer_Name])} -> Paul Baker | H2: =COUNTIF(Table1[Customer_Name],G2) -> 8 | I2: =IF(COUNTIF($K$21:$K$27,G2)>0,"Match","No Match") -> No Match | K2: {=_xlfn.UNIQUE(Table1[Product_Name])} -> Monitor | L2: =COUNTIF(Table1[Product_Name],K2) -> 26
A3: Joseph Jackson | B3: =SUMIF(Table1[Customer_Name],'groupby using formulas'!A3,Table1[Total_Amount]) -> 6949.84 | D3: Blender | E3: =SUMIF(Table1[Product_Name],D3,Table1[Total_Amount]) -> 5219.13 | G3: Joseph Jackson | H3: =COUNTIF(Table1[Customer_Name],G3) -> 5 | I3: =IF(COUNTIF($K$21:$K$27,G3)>0,"Match","No Match") -> No Match | K3: Blender | L3: =COUNTIF(Table1[Product_Name],K3) -> 29
A4: Kevin Scott | B4: =SUMIF(Table1[Customer_Name],'groupby using formulas'!A4,Table1[Total_Amount]) -> 3259.87 | D4: Bookshelf | E4: =SUMIF(Table1[Product_Name],D4,Table1[Total_Amount]) -> 15298.98 | G4: Kevin Scott | H4: =COUNTIF(Table1[Customer_Name],G4) -> 6 | I4: =IF(COUNTIF($K$21:$K$27,G4)>0,"Match","No Match") -> No Match | K4: Bookshelf | L4: =COUNTIF(Table1[Product_Name],K4) -> 35
A5: Kathleen Bennett | B5: =SUMIF(Table1[Customer_Name],'groupby using formulas'!A5,Table1[Total_Amount]) -> 4309.81 | D5: Headphones | E5: =SUMIF(Table1[Product_Name],D5,Table1[Total_Amount]) -> 7049.53 | G5: Kathleen Bennett | H5: =COUNTIF(Table1[Customer_Name],G5) -> 6 | I5: =IF(COUNTIF($K$21:$K$27,G5)>0,"Match","No Match") -> No Match | K5: Headphones | L5: =COUNTIF(Table1[Product_Name],K5) -> 16
A6: Michael Brown | B6: =SUMIF(Table1[Customer_Name],'groupby using formulas'!A6,Table1[Total_Amount]) -> 6169.74 | D6: Laptop | E6: =SUMIF(Table1[Product_Name],D6,Table1[Total_Amount]) -> 67499.25 | G6: Michael Brown | H6: =COUNTIF(Table1[Customer_Name],G6) -> 9 | I6: =IF(COUNTIF($K$21:$K$27,G6)>0,"Match","No Match") -> No Match | K6: Laptop | L6: =COUNTIF(Table1[Product_Name],K6) -> 24
A7: Dorothy Nelson | B7: =SUMIF(Table1[Customer_Name],'groupby using formulas'!A7,Table1[Total_Amount]) -> 8269.79 | D7: Smartphone | E7: =SUMIF(Table1[Product_Name],D7,Table1[Total_Amount]) -> 67199.04 | G7: Dorothy Nelson | H7: =COUNTIF(Table1[Customer_Name],G7) -> 6 | I7: =IF(COUNTIF($K$21:$K$27,G7)>0,"Match","No Match") -> No Match | K7: Smartphone | L7: =COUNTIF(Table1[Product_Name],K7) -> 31
A8: Charles Allen | B8: =SUMIF(Table1[Customer_Name],'groupby using formulas'!A8,Table1[Total_Amount]) -> 5089.73 | D8: Desk | E8: =SUMIF(Table1[Product_Name],D8,Table1[Total_Amount]) -> 23399.22 | G8: Charles Allen | H8: =COUNTIF(Table1[Customer_Name],G8) -> 9 | I8: =IF(COUNTIF($K$21:$K$27,G8)>0,"Match","No Match") -> No Match | K8: Desk | L8: =COUNTIF(Table1[Product_Name],K8) -> 26
A9: Robert Thomas | B9: =SUMIF(Table1[Customer_Name],'groupby using formulas'!A9,Table1[Total_Amount]) -> 3509.9 | D9: Coffee Maker | E9: =SUMIF(Table1[Product_Name],D9,Table1[Total_Amount]) -> 3119.61 | G9: Robert Thomas | H9: =COUNTIF(Table1[Customer_Name],G9) -> 5 | I9: =IF(COUNTIF($K$21:$K$27,G9)>0,"Match","No Match") -> No Match | K9: Coffee Maker | L9: =COUNTIF(Table1[Product_Name],K9) -> 14
A10: Karen Hill | B10: =SUMIF(Table1[Customer_Name],'groupby using formulas'!A10,Table1[Total_Amount]) -> 8009.77 | D10: Keyboard | E10: =SUMIF(Table1[Product_Name],D10,Table1[Total_Amount]) -> 8009.11 | G10: Karen Hill | H10: =COUNTIF(Table1[Customer_Name],G10) -> 8 | I10: =IF(COUNTIF($K$21:$K$27,G10)>0,"Match","No Match") -> No Match | K10: Keyboard | L10: =COUNTIF(Table1[Product_Name],K10) -> 34
A11: Susan Green | B11: =SUMIF(Table1[Customer_Name],'groupby using formulas'!A11,Table1[Total_Amount]) -> 1979.89 | D11: Office Chair | E11: =SUMIF(Table1[Product_Name],D11,Table1[Total_Amount]) -> 10399.48 | G11: Susan Green | H11: =COUNTIF(Table1[Customer_Name],G11) -> 4 | I11: =IF(COUNTIF($K$21:$K$27,G11)>0,"Match","No Match") -> No Match | K11: Office Chair | L11: =COUNTIF(Table1[Product_Name],K11) -> 15
A12: Peter Richardson | B12: =SUMIF(Table1[Customer_Name],'groupby using formulas'!A12,Table1[Total_Amount]) -> 5949.85 | G12: Peter Richardson | H12: =COUNTIF(Table1[Customer_Name],G12) -> 5 | I12: =IF(COUNTIF($K$21:$K$27,G12)>0,"Match","No Match") -> No Match
A13: Dennis Gray | B13: =SUMIF(Table1[Customer_Name],'groupby using formulas'!A13,Table1[Total_Amount]) -> 479.92 | G13: Dennis Gray | H13: =COUNTIF(Table1[Customer_Name],G13) -> 2 | I13: =IF(COUNTIF($K$21:$K$27,G13)>0,"Match","No Match") -> No Match
A14: Michelle Rogers | B14: =SUMIF(Table1[Customer_Name],'groupby using formulas'!A14,Table1[Total_Amount]) -> 4199.94 | G14: Michelle Rogers | H14: =COUNTIF(Table1[Customer_Name],G14) -> 2 | I14: =IF(COUNTIF($K$21:$K$27,G14)>0,"Match","No Match") -> No Match | K14: Most Sold product | L14: Top customer
A15: George Adams | B15: =SUMIF(Table1[Customer_Name],'groupby using formulas'!A15,Table1[Total_Amount]) -> 3779.93 | G15: George Adams | H15: =COUNTIF(Table1[Customer_Name],G15) -> 3 | I15: =IF(COUNTIF($K$21:$K$27,G15)>0,"Match","No Match") -> No Match | K15: =INDEX(K2:K11,MATCH(MAX(L2:L11),L2:L11,0)) -> Bookshelf | L15: =INDEX(G2:G51,MATCH(MAX(H2:H51),H2:H51,0)) -> Mark Carter
A16: Mark Carter | B16: =SUMIF(Table1[Customer_Name],'groupby using formulas'!A16,Table1[Total_Amount]) -> 15659.65 | G16: Mark Carter | H16: =COUNTIF(Table1[Customer_Name],G16) -> 12 | I16: =IF(COUNTIF($K$21:$K$27,G16)>0,"Match","No Match") -> No Match
A17: Maria Garcia | B17: =SUMIF(Table1[Customer_Name],'groupby using formulas'!A17,Table1[Total_Amount]) -> 1909.93 | G17: Maria Garcia | H17: =COUNTIF(Table1[Customer_Name],G17) -> 4 | I17: =IF(COUNTIF($K$21:$K$27,G17)>0,"Match","No Match") -> No Match
A18: Virginia Sanders | B18: =SUMIF(Table1[Customer_Name],'groupby using formulas'!A18,Table1[Total_Amount]) -> 4789.79 | G18: Virginia Sanders | H18: =COUNTIF(Table1[Customer_Name],G18) -> 6 | I18: =IF(COUNTIF($K$21:$K$27,G18)>0,"Match","No Match") -> No Match
A19: Barbara Young | B19: =SUMIF(Table1[Customer_Name],'groupby using formulas'!A19,Table1[Total_Amount]) -> 10649.8 | G19: Barbara Young | H19: =COUNTIF(Table1[Customer_Name],G19) -> 5 | I19: =IF(COUNTIF($K$21:$K$27,G19)>0,"Match","No Match") -> No Match
A20: Patricia Moore | B20: =SUMIF(Table1[Customer_Name],'groupby using formulas'!A20,Table1[Total_Amount]) -> 9799.73 | G20: Patricia Moore | H20: =COUNTIF(Table1[Customer_Name],G20) -> 8 | I20: =IF(COUNTIF($K$21:$K$27,G20)>0,"Match","No Match") -> No Match
A21: Cynthia Price | B21: =SUMIF(Table1[Customer_Name],'groupby using formulas'!A21,Table1[Total_Amount]) -> 3769.83 | G21: Cynthia Price | H21: =COUNTIF(Table1[Customer_Name],G21) -> 5 | I21: =IF(COUNTIF($K$21:$K$27,G21)>0,"Match","No Match") -> No Match
A22: Nancy Collins | B22: =SUMIF(Table1[Customer_Name],'groupby using formulas'!A22,Table1[Total_Amount]) -> 4189.77 | G22: Nancy Collins | H22: =COUNTIF(Table1[Customer_Name],G22) -> 6 | I22: =IF(COUNTIF($K$21:$K$27,G22)>0,"Match","No Match") -> No Match
A23: Linda Martin | B23: =SUMIF(Table1[Customer_Name],'groupby using formulas'!A23,Table1[Total_Amount]) -> 1289.9 | G23: Linda Martin | H23: =COUNTIF(Table1[Customer_Name],G23) -> 4 | I23: =IF(COUNTIF($K$21:$K$27,G23)>0,"Match","No Match") -> No Match
A24: Helen Roberts | B24: =SUMIF(Table1[Customer_Name],'groupby using formulas'!A24,Table1[Total_Amount]) -> 6459.79 | G24: Helen Roberts | H24: =COUNTIF(Table1[Customer_Name],G24) -> 7 | I24: =IF(COUNTIF($K$21:$K$27,G24)>0,"Match","No Match") -> No Match
A25: Edward Mitchell | B25: =SUMIF(Table1[Customer_Name],'groupby using formulas'!A25,Table1[Total_Amount]) -> 11919.77 | G25: Edward Mitchell | H25: =COUNTIF(Table1[Customer_Name],G25) -> 6 | I25: =IF(COUNTIF($K$21:$K$27,G25)>0,"Match","No Match") -> No Match
A26: Lisa Anderson | B26: =SUMIF(Table1[Customer_Name],'groupby using formulas'!A26,Table1[Total_Amount]) -> 2039.8 | G26: Lisa Anderson | H26: =COUNTIF(Table1[Customer_Name],G26) -> 5 | I26: =IF(COUNTIF($K$21:$K$27,G26)>0,"Match","No Match") -> No Match
A27: Emma Wilson | B27: =SUMIF(Table1[Customer_Name],'groupby using formulas'!A27,Table1[Total_Amount]) -> 1229.88 | G27: Emma Wilson | H27: =COUNTIF(Table1[Customer_Name],G27) -> 5 | I27: =IF(COUNTIF($K$21:$K$27,G27)>0,"Match","No Match") -> No Match
... A51: John Smith | B51: =SUMIF(Table1[Customer_Name],'groupby using formulas'!A51,Table1[Total_Amount]) -> 599.96 | G51: John Smith | H51: =COUNTIF(Table1[Customer_Name],G51) -> 1 | I51: =IF(COUNTIF($K$21:$K$27,G51)>0,"Match","No Match") -> No Match

Sheet what if
A1: Goal sheak
A2: product name | B2: Monitor
A3: product price | B3: 249.99
A4: quantity sold | B4: 200.008
A5: total amount | B5: 50000
A6: target | B6: 50000
A8: scenario
A9: unit price | B9: 80
A10: quantity | B10: 30
A11: discount % | B11: 0.2
A12: total slaes | B12: =B9*B10*(1-B11) -> 1920

Sheet Scenario Summary 3
B2: Scenario Summary
D3: Current Values: | E3: Best case | F3: Average Case | G3: worst case
E4: Created by MAYUR MAKVANA on 18-01-2026 Modified by MAYUR MAKVANA on 18-01-2026 | F4: Created by MAYUR MAKVANA on 18-01-2026 | G4: Created by MAYUR MAKVANA on 18-01-2026
B5: Changing Cells:
C6: $B$9 | D6: 80 | E6: 100 | F6: 120 | G6: 80
C7: $B$10 | D7: 30 | E7: 50 | F7: 70 | G7: 30
C8: $B$11 | D8: 0.2 | E8: 0.1 | F8: 0.05 | G8: 0.2
B9: Result Cells:
C10: $B$12 | D10: 1920 | E10: 4500 | F10: 7980 | G10: 1920
B11: Notes: Current Values column represents values of changing cells at
B12: time Scenario Summary Report was created. Changing cells for each
B13: scenario are highlighted in gray.

Sheet regression
A1: Quantity VS Total Amount
A2: SUMMARY OUTPUT
A4: Regression Statistics
A5: Multiple R | B5: 0.45809869
A6: R Square | B6: 0.20985441
A7: Adjusted R Square | B7: 0.20665544
A8: Standard Error | B8: 921.40854
A9: Observations | B9: 249
A11: ANOVA
B12: df | C12: SS | D12: MS | E12: F | F12: Significance F
A13: Regression | B13: 1 | C13: 55694513 | D13: 55694513 | E13: 65.60062 | F13: 2.5391277e-14
A14: Residual | B14: 247 | C14: 2.0970144e+08 | D14: 848993.7
A15: Total | B15: 248 | C15: 2.6539596e+08
B17: Coefficients | C17: Standard Error | D17: t Stat | E17: P-value | F17: Lower 95% | G17: Upper 95% | H17: Lower 95.0% | I17: Upper 95.0%
A18: Intercept | B18: -148.18856 | C18: 143.94399 | D18: -1.0294877 | E18: 0.30425761 | F18: -431.70277 | G18: 135.32564 | H18: -431.70277 | I18: 135.32564
A19: 3 | B19: 353.7886 | C19: 43.680728 | D19: 8.0994209 | E19: 2.5391277e-14 | F19: 267.7544 | G19: 439.82281 | H19: 267.7544 | I19: 439.82281
